colna/__init__.py
colna/analyticnetwork.py
colna/lossconversion.py
complex_linear_network_analyzer-1.0.4.dist-info/LICENSE.txt
complex_linear_network_analyzer-1.0.4.dist-info/METADATA
complex_linear_network_analyzer-1.0.4.dist-info/WHEEL
complex_linear_network_analyzer-1.0.4.dist-info/top_level.txt
complex_linear_network_analyzer-1.0.4.dist-info/RECORD
