Metadata-Version: 2.1
Name: complex-linear-network-analyzer
Version: 1.0.4
Summary: Computes analytically the output of complex valued, linear networks.
Home-page: https://github.com/IBM/complex-linear-network-analyzer
Author: Lorenz K. Müller, Pascal Stark
Author-email: crk@zurich.ibm.com
License: UNKNOWN
Platform: UNKNOWN
Classifier: Programming Language :: Python :: 3
Classifier: License :: OSI Approved :: Apache Software License
Classifier: Operating System :: OS Independent
Requires-Dist: tqdm
Requires-Dist: scipy
Requires-Dist: numpy
Requires-Dist: matplotlib
Provides-Extra: visualization
Requires-Dist: graphviz ; extra == 'visualization'
